fastlane/__init__.py
fastlane/api/__init__.py
fastlane/api/app.py
fastlane/api/enqueue.py
fastlane/api/execution.py
fastlane/api/gzipped.py
fastlane/api/healthcheck.py
fastlane/api/helpers.py
fastlane/api/metrics.py
fastlane/api/routes.py
fastlane/api/status.py
fastlane/api/stream.py
fastlane/api/task.py
fastlane/cli/__init__.py
fastlane/cli/api.py
fastlane/cli/core.py
fastlane/cli/prune.py
fastlane/cli/worker.py
fastlane/config/__init__.py
fastlane/config/local.conf
fastlane/errors/__init__.py
fastlane/errors/sentry.py
fastlane/helpers.py
fastlane/models/__init__.py
fastlane/models/categories.py
fastlane/models/job.py
fastlane/models/job_execution.py
fastlane/models/task.py
fastlane/queue.py
fastlane/templates/stream.html
fastlane/utils.py
fastlane/worker/__init__.py
fastlane/worker/docker/__init__.py
fastlane/worker/docker/api.py
fastlane/worker/docker/executor.py
fastlane/worker/docker/pool.py
fastlane/worker/errors.py
fastlane/worker/job.py
fastlane/worker/webhooks.py
fastlane-2.2.3.dist-info/entry_points.txt
fastlane-2.2.3.dist-info/LICENSE
fastlane-2.2.3.dist-info/WHEEL
fastlane-2.2.3.dist-info/METADATA
fastlane-2.2.3.dist-info/RECORD
