Metadata-Version: 2.1
Name: fastlane
Version: 2.2.3
Summary: fastlane is a redis and docker based queueing service.
Home-page: UNKNOWN
License: UNKNOWN
Author: Bernardo Heynemann
Author-email: heynemann@gmail.com
Requires-Python: >=3.6,<4.0
Classifier: Programming Language :: Python :: 3
Classifier: Programming Language :: Python :: 3.6
Classifier: Programming Language :: Python :: 3.7
Requires-Dist: Flask-BasicAuth (>=0.2.0,<0.3.0)
Requires-Dist: Flask-Redis-Sentinel (>=2.0,<3.0)
Requires-Dist: Redis-Sentinel-Url (>=1.0,<2.0)
Requires-Dist: click (>=6.7,<7.0)
Requires-Dist: croniter (>=0.3.29,<0.4.0)
Requires-Dist: derpconf (>=0.8.2,<0.9.0)
Requires-Dist: docker (>=3.4,<4.0)
Requires-Dist: flask (>=1.0,<2.0)
Requires-Dist: flask-cors (>=3.0,<4.0)
Requires-Dist: flask-mongoengine (>=0.9.5,<0.10.0)
Requires-Dist: flask-redis (>=0.3.0,<0.4.0)
Requires-Dist: flask-sockets (>=0.2.1,<0.3.0)
Requires-Dist: gevent-websocket
Requires-Dist: pybreaker (>=0.4.5,<0.5.0)
Requires-Dist: python-dateutil (>=2.7,<3.0)
Requires-Dist: pyyaml (>=4.2b1,<5.0)
Requires-Dist: raven (>=6.9,<7.0)
Requires-Dist: redis (>=3.1.0,<4.0.0)
Requires-Dist: requests (>=2.21,<3.0)
Requires-Dist: sentry-sdk (==0.5.5)
Requires-Dist: structlog (>=18.1,<19.0)
Requires-Dist: ujson (>=1.35,<2.0)
Requires-Dist: wsaccel (>=0.6.2,<0.7.0)
